CHANGES.txt
LICENSE.txt
MANIFEST.in
README.txt
setup.py
appypi/ApplicationController.py
appypi/TerminalView.py
appypi/__init__.py
appypi/cmdline.py
appypi/docopt.py
appypi/models.py
appypi/pypi.py
appypi/settings.py
appypi/utils.py
appypi.egg-info/PKG-INFO
appypi.egg-info/SOURCES.txt
appypi.egg-info/dependency_links.txt
appypi.egg-info/requires.txt
appypi.egg-info/top_level.txt
appypi/templates/binfile_template
appypi/templates/bootstrapfile_template
bin/appypi
docs/Makefile
docs/changelog.rst
docs/conf.py
docs/index.rst
docs/install.rst
docs/technical.rst
docs/usage.rst
docs/_build/doctrees/changelog.doctree
docs/_build/doctrees/environment.pickle
docs/_build/doctrees/index.doctree
docs/_build/doctrees/install.doctree
docs/_build/doctrees/technical.doctree
docs/_build/doctrees/usage.doctree
docs/_build/html/.buildinfo
docs/_build/html/changelog.html
docs/_build/html/genindex.html
docs/_build/html/index.html
docs/_build/html/install.html
docs/_build/html/objects.inv
docs/_build/html/search.html
docs/_build/html/searchindex.js
docs/_build/html/technical.html
docs/_build/html/usage.html
docs/_build/html/_sources/changelog.txt
docs/_build/html/_sources/index.txt
docs/_build/html/_sources/install.txt
docs/_build/html/_sources/technical.txt
docs/_build/html/_sources/usage.txt
docs/_build/html/_static/ajax-loader.gif
docs/_build/html/_static/basic.css
docs/_build/html/_static/comment-bright.png
docs/_build/html/_static/comment-close.png
docs/_build/html/_static/comment.png
docs/_build/html/_static/doctools.js
docs/_build/html/_static/down-pressed.png
docs/_build/html/_static/down.png
docs/_build/html/_static/file.png
docs/_build/html/_static/jquery.js
docs/_build/html/_static/minus.png
docs/_build/html/_static/nature.css
docs/_build/html/_static/plus.png
docs/_build/html/_static/pygments.css
docs/_build/html/_static/searchtools.js
docs/_build/html/_static/underscore.js
docs/_build/html/_static/up-pressed.png
docs/_build/html/_static/up.png
docs/_build/html/_static/websupport.js
tests/__init__.py
tests/test_ApplicationController.py
tests/test_manual.py
tests/test_models.py
tests/test_utils.py
